llmfastdev/__init__.py
llmfastdev/llamafile_client.py
llmfastdev-0.0.1.dist-info/licenses/LICENSE
llmfastdev-0.0.1.dist-info/METADATA
llmfastdev-0.0.1.dist-info/WHEEL
llmfastdev-0.0.1.dist-info/top_level.txt
llmfastdev-0.0.1.dist-info/RECORD
