Metadata-Version: 2.4
Name: llmfastdev
Version: 0.0.1
Summary: A Python client for interacting with llamafile local LLM instances
Author-email: Your Name <your.email@example.com>
Project-URL: Homepage, https://github.com/yourusername/llmfastdev
Project-URL: Bug Tracker, https://github.com/yourusername/llmfastdev/issues
Classifier: Development Status :: 3 - Alpha
Classifier: Intended Audience :: Developers
Classifier: License :: OSI Approved :: MIT License
Classifier: Operating System :: OS Independent
Classifier: Programming Language :: Python :: 3
Classifier: Programming Language :: Python :: 3.7
Classifier: Programming Language :: Python :: 3.8
Classifier: Programming Language :: Python :: 3.9
Classifier: Programming Language :: Python :: 3.10
Classifier: Programming Language :: Python :: 3.11
Classifier: Programming Language :: Python :: 3.12
Requires-Python: >=3.7
License-File: LICENSE
Requires-Dist: requests>=2.25.0
Dynamic: license-file
